thermo_lib/__init__.py
thermo_lib/thermo_lib.py
JWs_thermo_lib-0.0.1.dist-info/LICENSE
JWs_thermo_lib-0.0.1.dist-info/METADATA
JWs_thermo_lib-0.0.1.dist-info/WHEEL
JWs_thermo_lib-0.0.1.dist-info/top_level.txt
JWs_thermo_lib-0.0.1.dist-info/RECORD
