Metadata-Version: 2.1
Name: JWs_thermo_lib
Version: 0.0.1
Summary: Library for thermochemical calculations.
Author-email: Jonas Weitzel <jonas.weitzel@gmail.com>
Classifier: Programming Language :: Python :: 3
Classifier: License :: OSI Approved :: MIT License
Classifier: Operating System :: OS Independent
Requires-Python: >=3.8
License-File: LICENSE
